ExtractLevelDomain.py
setup.py
ExtractLevelDomain.egg-info/PKG-INFO
ExtractLevelDomain.egg-info/SOURCES.txt
ExtractLevelDomain.egg-info/dependency_links.txt
ExtractLevelDomain.egg-info/top_level.txt